{
  "concept_id": "secret_requirement_readiness",
  "canonical_name": "SecretRequirementReadiness",
  "short_definition": "The pair of secret requirement and readiness states for a launch or projection dependency.",
  "description": "SecretRequirementReadiness models whether a secret is required, where it is expected, how it is represented, whether it is readable, and what redacted diagnostics or repair guidance should be shown. It treats secrets as capabilities rather than configuration values.",
  "kind": "policy",
  "status": "draft",
  "aliases": ["secret requirement", "secret readiness", "provider secret readiness"],
  "deprecated_aliases": [],
  "anti_aliases": ["raw secret value", "env dump", "credential blob"],
  "boundaries": [
    "Not a vault implementation.",
    "Not raw secret disclosure.",
    "Not a generic configuration object."
  ],
  "relations": [
    { "kind": "depends_on", "concept_id": "runtime_capability_profile" },
    { "kind": "depends_on", "concept_id": "host_profile" }
  ],
  "owner_surface": "Narada secret governance doctrine",
  "authority": {
    "kind": "documentation_and_implementation",
    "ref": "docs/concepts/capability-governed-secret-management.md",
    "notes": "Secret requirements and readiness are already described as capability-governed launch/projection dependencies."
  },
  "schemas": ["docs/concepts/capability-governed-secret-management.md"],
  "docs": ["docs/concepts/capability-governed-secret-management.md"],
  "tasks": ["1697", "first-class-system-objects"],
  "code_refs": ["packages/agent-start/src/narada-agent-start.ts", "packages/layers/cli/src/commands/doctor.ts"],
  "tests": ["packages/agent-start/test/option-contract.test.mjs", "packages/layers/cli/test/commands/doctor.test.ts"],
  "examples": ["codex-subscription readiness with missing/available/unreadable diagnostics"],
  "counterexamples": ["printing secret values in launch results"],
  "open_questions": ["Should requirement/readiness be a single object or two linked records in the registry?"],
  "confidence": { "cl": 0.97, "basis": "The secret-management doctrine already defines locus-aware secret references, redaction, and preflight expectations." },
  "reviewed_at": "2026-07-02T22:00:00.000Z"
}